pd2ml/__init__.py
pd2ml/common.py
pd2ml/interface.py
pd2ml/loader.py
pd2ml/loader_ext.py
pd2ml/manager.py
pd2ml/utils.py
pd2ml-0.1.0.dist-info/LICENSE
pd2ml-0.1.0.dist-info/METADATA
pd2ml-0.1.0.dist-info/WHEEL
pd2ml-0.1.0.dist-info/top_level.txt
pd2ml-0.1.0.dist-info/RECORD
