Metadata-Version: 2.1
Name: pd2ml
Version: 0.1.0
Summary: A Python package that provides an efficient way to upload pandas DataFrame to MySQL and download from the database table into a DataFrame.
Home-page: https://github.com/TanyeeZhang/pd2ml
Author: Tanyee Zhang
Author-email: 676761828@qq.com
License: UNKNOWN
Platform: UNKNOWN
Classifier: Programming Language :: Python :: 3
Classifier: License :: OSI Approved :: MIT License
Classifier: Operating System :: OS Independent
